skpcp/__init__.py
skpcp/pcp.py
skpcp-0.1.0.dist-info/WHEEL
skpcp-0.1.0.dist-info/METADATA
skpcp-0.1.0.dist-info/RECORD
