Metadata-Version: 2.3
Name: skpcp
Version: 0.1.0
Summary: Principal component pursuit built on top of scikit-learn
Author: Mohammadjavad Vakili
Author-email: Mohammadjavad Vakili <mohammadjavad.vakili@gmail.com>
Requires-Dist: numpy
Requires-Dist: scikit-learn
Requires-Dist: ruff==0.9.10 ; extra == 'dev'
Requires-Dist: pre-commit==4.1.0 ; extra == 'dev'
Requires-Dist: sphinx<8.2 ; extra == 'docs'
Requires-Dist: sphinx-book-theme ; extra == 'docs'
Requires-Dist: sphinx-copybutton ; extra == 'docs'
Requires-Dist: sphinx-autodoc-typehints ; extra == 'docs'
Requires-Dist: nbsphinx ; extra == 'docs'
Requires-Dist: ipython ; extra == 'docs'
Requires-Dist: matplotlib ; extra == 'docs'
Requires-Dist: nbformat==5.4.0 ; extra == 'docs'
Requires-Dist: ipython ; extra == 'docs'
Requires-Dist: notebook ; extra == 'docs'
Requires-Dist: pytest ; extra == 'tests'
Requires-Dist: pytest-cov ; extra == 'tests'
Requires-Dist: scipy ; extra == 'tests'
Requires-Python: >=3.11
Provides-Extra: dev
Provides-Extra: docs
Provides-Extra: tests
